tests/fixtures/__init__.py
yasmin/__init__.py
yasmin/constants.py
yasmin/core.py
yasmin/exceptions.py
yasmin/helpers.py
yasmin-0.1.0.dist-info/DESCRIPTION.rst
yasmin-0.1.0.dist-info/METADATA
yasmin-0.1.0.dist-info/RECORD
yasmin-0.1.0.dist-info/WHEEL
yasmin-0.1.0.dist-info/metadata.json
yasmin-0.1.0.dist-info/top_level.txt
yasmin-0.1.0.dist-info/zip-safe
